gitme/__init__.py
gitme/cli.py
gitme/config.py
gitme/git_diff.py
gitme/llm_client.py
gitme/storage.py
gitme_cli-0.9.1.dist-info/METADATA
gitme_cli-0.9.1.dist-info/WHEEL
gitme_cli-0.9.1.dist-info/entry_points.txt
gitme_cli-0.9.1.dist-info/licenses/LICENSE
gitme_cli-0.9.1.dist-info/RECORD
