Metadata-Version: 2.4
Name: gitme-cli
Version: 0.9.1
Summary: Git actions simplified
Project-URL: Homepage, https://github.com/wangjing0/gitme
Project-URL: Repository, https://github.com/wangjing0/gitme
Author-email: Jing Wang <jingwang.physics@gmail.com>
License-Expression: MIT
License-File: LICENSE
Keywords: ai,claude,commit,generator,git,message,openai
Classifier: Development Status :: 4 - Beta
Classifier: Intended Audience :: Developers
Classifier: Topic :: Software Development :: Version Control :: Git
Requires-Python: >=3.8
Requires-Dist: anthropic>=0.70.0
Requires-Dist: click>=8.0.0
Provides-Extra: openai
Requires-Dist: openai>=1.0.0; extra == 'openai'
